UCSDYelpData-0.0.4.dist-info/DESCRIPTION.rst
UCSDYelpData-0.0.4.dist-info/entry_points.txt
UCSDYelpData-0.0.4.dist-info/METADATA
UCSDYelpData-0.0.4.dist-info/metadata.json
UCSDYelpData-0.0.4.dist-info/pbr.json
UCSDYelpData-0.0.4.dist-info/RECORD
UCSDYelpData-0.0.4.dist-info/top_level.txt
UCSDYelpData-0.0.4.dist-info/WHEEL
yelp/__init__.py
yelp/__main__.py
yelp/__version__.py
yelp/analysis.py
yelp/user.py
